dandischema/__init__.py
dandischema/_version.py
dandischema/consts.py
dandischema/exceptions.py
dandischema/metadata.py
dandischema/models.py
dandischema/py.typed
dandischema/types.py
dandischema/utils.py
dandischema/datacite/__init__.py
dandischema/datacite/schema/README.md
dandischema/datacite/schema/datacite-4.3-17-gaa5db56.json
dandischema/datacite/schema/datacite-4.3-72-g732cc7e.json
dandischema/datacite/schema/inveniosoftware-4.3-66-g24fc2ba.json
dandischema/datacite/schema/inveniosoftware-4.5-81-g160250d.json
dandischema/datacite/tests/__init__.py
dandischema/datacite/tests/test_datacite.py
dandischema/digests/__init__.py
dandischema/digests/dandietag.py
dandischema/digests/tests/__init__.py
dandischema/digests/tests/test_dandietag.py
dandischema/tests/__init__.py
dandischema/tests/conftest.py
dandischema/tests/test_metadata.py
dandischema/tests/test_models.py
dandischema/tests/test_utils.py
dandischema/tests/utils.py
dandischema/tests/data/metadata/asset3_01.json
dandischema/tests/data/metadata/asset3_02.json
dandischema/tests/data/metadata/asset4_01.json
dandischema/tests/data/metadata/asset4_02.json
dandischema/tests/data/metadata/asset_001.json
dandischema/tests/data/metadata/meta_000004.json
dandischema/tests/data/metadata/meta_000004old.json
dandischema/tests/data/metadata/meta_000008.json
dandischema-0.11.1.dist-info/licenses/LICENSE
dandischema-0.11.1.dist-info/METADATA
dandischema-0.11.1.dist-info/WHEEL
dandischema-0.11.1.dist-info/top_level.txt
dandischema-0.11.1.dist-info/RECORD
