Metadata-Version: 2.4
Name: dandischema
Version: 0.11.1
Summary: Schemata for DANDI archive project
Home-page: http://dandiarchive.org
Author: DANDI developers
Author-email: team@dandiarchive.org
Maintainer: Yaroslav O. Halchenko
Maintainer-email: debian@onerussian.com
License: Apache 2.0
Project-URL: Source Code, https://github.com/dandi/dandischema
Platform: OS Independent
Classifier: Development Status :: 1 - Planning
Classifier: Environment :: Console
Classifier: Intended Audience :: Science/Research
Classifier: License :: OSI Approved :: Apache Software License
Classifier: Operating System :: OS Independent
Classifier: Programming Language :: Python
Classifier: Programming Language :: Python :: 3.9
Classifier: Programming Language :: Python :: 3.10
Classifier: Programming Language :: Python :: 3.11
Classifier: Programming Language :: Python :: 3.12
Classifier: Topic :: Scientific/Engineering
Requires-Python: >=3.9
License-File: LICENSE
Requires-Dist: jsonschema[format]
Requires-Dist: pydantic[email]~=2.4
Requires-Dist: requests
Requires-Dist: zarr_checksum
Provides-Extra: style
Requires-Dist: flake8; extra == "style"
Requires-Dist: pre-commit; extra == "style"
Provides-Extra: test
Requires-Dist: mypy; extra == "test"
Requires-Dist: pytest; extra == "test"
Requires-Dist: pytest-cov; extra == "test"
Requires-Dist: pytest-rerunfailures; extra == "test"
Provides-Extra: all
Requires-Dist: flake8; extra == "all"
Requires-Dist: pre-commit; extra == "all"
Requires-Dist: mypy; extra == "all"
Requires-Dist: pytest; extra == "all"
Requires-Dist: pytest-cov; extra == "all"
Requires-Dist: pytest-rerunfailures; extra == "all"
Dynamic: license-file
